[{"postal_code":"20179","place_name":"Pensadores Mexicanos","place_type":"Fraccionamiento","county":"Aguascalientes","state":"Aguascalientes","city":"Aguascalientes"},{"postal_code":"20179","place_name":"Santa Margarita","place_type":"Fraccionamiento","county":"Aguascalientes","state":"Aguascalientes","city":"Aguascalientes"},{"postal_code":"20179","place_name":"Progreso","place_type":"Colonia","county":"Aguascalientes","state":"Aguascalientes","city":"Aguascalientes"},{"postal_code":"20179","place_name":"Las Cumbres","place_type":"Fraccionamiento","county":"Aguascalientes","state":"Aguascalientes","city":"Aguascalientes"},{"postal_code":"20179","place_name":"Pintores Mexicanos","place_type":"Fraccionamiento","county":"Aguascalientes","state":"Aguascalientes","city":"Aguascalientes"},{"postal_code":"20179","place_name":"Santa Regina","place_type":"Fraccionamiento","county":"Aguascalientes","state":"Aguascalientes","city":"Aguascalientes"},{"postal_code":"20179","place_name":"Luis Ortega Douglas","place_type":"Fraccionamiento","county":"Aguascalientes","state":"Aguascalientes","city":"Aguascalientes"},{"postal_code":"20179","place_name":"Cerro Alto","place_type":"Fraccionamiento","county":"Aguascalientes","state":"Aguascalientes","city":"Aguascalientes"}]