[{"postal_code":"21390","place_name":"Francisco I Madero","place_type":"Colonia","county":"Mexicali","state":"Baja California","city":"Mexicali"},{"postal_code":"21390","place_name":"Granjas Nuevas","place_type":"Colonia","county":"Mexicali","state":"Baja California","city":"Mexicali"},{"postal_code":"21390","place_name":"Ignacio Allende","place_type":"Colonia","county":"Mexicali","state":"Baja California","city":"Mexicali"},{"postal_code":"21390","place_name":"Haro Barnet","place_type":"Fraccionamiento","county":"Mexicali","state":"Baja California","city":"Mexicali"},{"postal_code":"21390","place_name":"Nueva 18 de Marzo","place_type":"Colonia","county":"Mexicali","state":"Baja California","city":"Mexicali"}]