[{"postal_code":"22710","place_name":"Costa del sol","place_type":"Fraccionamiento","county":"Playas de Rosarito","state":"Baja California","city":"Playas de Rosarito"},{"postal_code":"22710","place_name":"El Mañana","place_type":"Colonia","county":"Playas de Rosarito","state":"Baja California","city":"Playas de Rosarito"},{"postal_code":"22710","place_name":"Camino Alegre","place_type":"Colonia","county":"Playas de Rosarito","state":"Baja California","city":"Playas de Rosarito"},{"postal_code":"22710","place_name":"Popotla","place_type":"Colonia","county":"Playas de Rosarito","state":"Baja California","city":"Playas de Rosarito"},{"postal_code":"22710","place_name":"Playa Hermosa","place_type":"Colonia","county":"Playas de Rosarito","state":"Baja California","city":"Playas de Rosarito"},{"postal_code":"22710","place_name":"La Cascada","place_type":"Fraccionamiento","county":"Playas de Rosarito","state":"Baja California","city":"Playas de Rosarito"}]