[{"postal_code":"22839","place_name":"Los Laureles","place_type":"Fraccionamiento","county":"Ensenada","state":"Baja California","city":"Ensenada"},{"postal_code":"22839","place_name":"Villafontana","place_type":"Fraccionamiento","county":"Ensenada","state":"Baja California","city":"Ensenada"},{"postal_code":"22839","place_name":"Valle Verde","place_type":"Colonia","county":"Ensenada","state":"Baja California","city":"Ensenada"},{"postal_code":"22839","place_name":"Magisterial La Presa","place_type":"Fraccionamiento","county":"Ensenada","state":"Baja California","city":"Ensenada"}]