[{"postal_code":"25057","place_name":"Parajes de Oriente","place_type":"Fraccionamiento","county":"Saltillo","state":"Coahuila de Zaragoza","city":"Saltillo"},{"postal_code":"25057","place_name":"Colinas de San Francisco","place_type":"Fraccionamiento","county":"Saltillo","state":"Coahuila de Zaragoza","city":"Saltillo"},{"postal_code":"25057","place_name":"El Volcán","place_type":"Fraccionamiento","county":"Saltillo","state":"Coahuila de Zaragoza","city":"Saltillo"},{"postal_code":"25057","place_name":"Lomas de San Javier","place_type":"Colonia","county":"Saltillo","state":"Coahuila de Zaragoza","city":"Saltillo"},{"postal_code":"25057","place_name":"Jesús Cabello","place_type":"Colonia","county":"Saltillo","state":"Coahuila de Zaragoza","city":"Saltillo"},{"postal_code":"25057","place_name":"La Herradura","place_type":"Fraccionamiento","county":"Saltillo","state":"Coahuila de Zaragoza","city":"Saltillo"},{"postal_code":"25057","place_name":"Los Nogales II","place_type":"Fraccionamiento","county":"Saltillo","state":"Coahuila de Zaragoza","city":"Saltillo"}]