[{"postal_code":"25197","place_name":"La Esmeralda","place_type":"Colonia","county":"Saltillo","state":"Coahuila de Zaragoza","city":"Saltillo"},{"postal_code":"25197","place_name":"La Romita","place_type":"Colonia","county":"Saltillo","state":"Coahuila de Zaragoza","city":"Saltillo"},{"postal_code":"25197","place_name":"Ladrilleros","place_type":"Colonia","county":"Saltillo","state":"Coahuila de Zaragoza","city":"Saltillo"},{"postal_code":"25197","place_name":"Los Rosarios Popular","place_type":"Colonia","county":"Saltillo","state":"Coahuila de Zaragoza","city":"Saltillo"},{"postal_code":"25197","place_name":"El Morillo","place_type":"Fraccionamiento","county":"Saltillo","state":"Coahuila de Zaragoza","city":"Saltillo"},{"postal_code":"25197","place_name":"La Joyita","place_type":"Colonia","county":"Saltillo","state":"Coahuila de Zaragoza","city":"Saltillo"}]