[{"postal_code":"25870","place_name":"Independencia","place_type":"Colonia","county":"Castaños","state":"Coahuila de Zaragoza","city":"Castaños"},{"postal_code":"25870","place_name":"Héroes del 47","place_type":"Colonia","county":"Castaños","state":"Coahuila de Zaragoza","city":"Castaños"},{"postal_code":"25870","place_name":"Independencia Sur","place_type":"Colonia","county":"Castaños","state":"Coahuila de Zaragoza","city":"Castaños"},{"postal_code":"25870","place_name":"Emiliano Zapata","place_type":"Colonia","county":"Castaños","state":"Coahuila de Zaragoza","city":"Castaños"},{"postal_code":"25870","place_name":"Libertad","place_type":"Colonia","county":"Castaños","state":"Coahuila de Zaragoza","city":"Castaños"},{"postal_code":"25870","place_name":"Castaños Centro","place_type":"Colonia","county":"Castaños","state":"Coahuila de Zaragoza","city":"Castaños"},{"postal_code":"25870","place_name":"San José","place_type":"Fraccionamiento","county":"Castaños","state":"Coahuila de Zaragoza","city":"Castaños"},{"postal_code":"25870","place_name":"Libertad Oriente","place_type":"Colonia","county":"Castaños","state":"Coahuila de Zaragoza","city":"Castaños"},{"postal_code":"25870","place_name":"Venustiano Carranza","place_type":"Colonia","county":"Castaños","state":"Coahuila de Zaragoza","city":"Castaños"},{"postal_code":"25870","place_name":"21 de Marzo","place_type":"Fraccionamiento","county":"Castaños","state":"Coahuila de Zaragoza","city":"Castaños"},{"postal_code":"25870","place_name":"Independencia Norte","place_type":"Colonia","county":"Castaños","state":"Coahuila de Zaragoza","city":"Castaños"},{"postal_code":"25870","place_name":"Villas de Guadalupe","place_type":"Fraccionamiento","county":"Castaños","state":"Coahuila de Zaragoza","city":"Castaños"},{"postal_code":"25870","place_name":"California","place_type":"Colonia","county":"Castaños","state":"Coahuila de Zaragoza","city":"Castaños"},{"postal_code":"25870","place_name":"Santa Cecilia","place_type":"Fraccionamiento","county":"Castaños","state":"Coahuila de Zaragoza","city":"Castaños"},{"postal_code":"25870","place_name":"Colinas Independencia","place_type":"Fraccionamiento","county":"Castaños","state":"Coahuila de Zaragoza","city":"Castaños"}]