[{"postal_code":"28237","place_name":"La Gasera","place_type":"Colonia","county":"Manzanillo","state":"Colima","city":"Manzanillo"},{"postal_code":"28237","place_name":"Las Torres","place_type":"Colonia","county":"Manzanillo","state":"Colima","city":"Manzanillo"},{"postal_code":"28237","place_name":"Leandro Valle","place_type":"Colonia","county":"Manzanillo","state":"Colima","city":"Manzanillo"},{"postal_code":"28237","place_name":"Benito Juárez","place_type":"Colonia","county":"Manzanillo","state":"Colima","city":"Manzanillo"},{"postal_code":"28237","place_name":"Punta Grande","place_type":"Colonia","county":"Manzanillo","state":"Colima","city":"Manzanillo"}]