[{"postal_code":"30479","place_name":"Santa Catarina","place_type":"Barrio","county":"Villaflores","state":"Chiapas","city":"Villaflores"},{"postal_code":"30479","place_name":"Las Gardenias","place_type":"Colonia","county":"Villaflores","state":"Chiapas","city":"Villaflores"},{"postal_code":"30479","place_name":"Almacenes","place_type":"Barrio","county":"Villaflores","state":"Chiapas","city":"Villaflores"},{"postal_code":"30479","place_name":"Reforma","place_type":"Barrio","county":"Villaflores","state":"Chiapas","city":"Villaflores"},{"postal_code":"30479","place_name":"Guadalupe","place_type":"Barrio","county":"Villaflores","state":"Chiapas","city":"Villaflores"},{"postal_code":"30479","place_name":"Los Fraylescanos","place_type":"Colonia","county":"Villaflores","state":"Chiapas","city":"Villaflores"},{"postal_code":"30479","place_name":"Fraylescano","place_type":"Barrio","county":"Villaflores","state":"Chiapas","city":"Villaflores"},{"postal_code":"30479","place_name":"Huanacaxtle","place_type":"Fraccionamiento","county":"Villaflores","state":"Chiapas","city":"Villaflores"},{"postal_code":"30479","place_name":"Bicentenario","place_type":"Fraccionamiento","county":"Villaflores","state":"Chiapas","city":"Villaflores"},{"postal_code":"30479","place_name":"San Miguel","place_type":"Barrio","county":"Villaflores","state":"Chiapas","city":"Villaflores"},{"postal_code":"30479","place_name":"Siglo XXI","place_type":"Fraccionamiento","county":"Villaflores","state":"Chiapas","city":"Villaflores"},{"postal_code":"30479","place_name":"La Gironda","place_type":"Colonia","county":"Villaflores","state":"Chiapas","city":"Villaflores"},{"postal_code":"30479","place_name":"San Martín","place_type":"Barrio","county":"Villaflores","state":"Chiapas","city":"Villaflores"},{"postal_code":"30479","place_name":"Solidaridad","place_type":"Colonia","county":"Villaflores","state":"Chiapas","city":"Villaflores"},{"postal_code":"30479","place_name":"Santa Cruz la Unión","place_type":"Fraccionamiento","county":"Villaflores","state":"Chiapas","city":"Villaflores"}]