[{"postal_code":"31050","place_name":"Rincones de Santa Rosa","place_type":"Unidad habitacional","county":"Chihuahua","state":"Chihuahua","city":"Chihuahua"},{"postal_code":"31050","place_name":"Dale","place_type":"Colonia","county":"Chihuahua","state":"Chihuahua","city":"Chihuahua"},{"postal_code":"31050","place_name":"Santa Rosa","place_type":"Colonia","county":"Chihuahua","state":"Chihuahua","city":"Chihuahua"},{"postal_code":"31050","place_name":"Pablo Amaya Norte","place_type":"Colonia","county":"Chihuahua","state":"Chihuahua","city":"Chihuahua"},{"postal_code":"31050","place_name":"Bellavista","place_type":"Colonia","county":"Chihuahua","state":"Chihuahua","city":"Chihuahua"},{"postal_code":"31050","place_name":"Pablo Amaya Sur","place_type":"Colonia","county":"Chihuahua","state":"Chihuahua","city":"Chihuahua"},{"postal_code":"31050","place_name":"Melchor Ocampo","place_type":"Colonia","county":"Chihuahua","state":"Chihuahua","city":"Chihuahua"}]