[{"postal_code":"32401","place_name":"Rinconada de las Flores","place_type":"Fraccionamiento","county":"Juárez","state":"Chihuahua","city":"Juárez"},{"postal_code":"32401","place_name":"Paseo de las Flores","place_type":"Fraccionamiento","county":"Juárez","state":"Chihuahua","city":"Juárez"},{"postal_code":"32401","place_name":"Napoli","place_type":"Condominio","county":"Juárez","state":"Chihuahua","city":"Juárez"},{"postal_code":"32401","place_name":"Génova","place_type":"Condominio","county":"Juárez","state":"Chihuahua","city":"Juárez"},{"postal_code":"32401","place_name":"Palermo","place_type":"Condominio","county":"Juárez","state":"Chihuahua","city":"Juárez"},{"postal_code":"32401","place_name":"Las Quintas","place_type":"Fraccionamiento","county":"Juárez","state":"Chihuahua","city":"Juárez"}]