[{"postal_code":"32575","place_name":"Los Ángeles (Horizonte del Sur)","place_type":"Condominio","county":"Juárez","state":"Chihuahua","city":"Juárez"},{"postal_code":"32575","place_name":"Paraguay (Rinconada de las Torres)","place_type":"Condominio","county":"Juárez","state":"Chihuahua","city":"Juárez"},{"postal_code":"32575","place_name":"Senderos de Oriente","place_type":"Fraccionamiento","county":"Juárez","state":"Chihuahua","city":"Juárez"},{"postal_code":"32575","place_name":"Versalles Niza","place_type":"Fraccionamiento","county":"Juárez","state":"Chihuahua","city":"Juárez"},{"postal_code":"32575","place_name":"Horizontes del Sur","place_type":"Fraccionamiento","county":"Juárez","state":"Chihuahua","city":"Juárez"},{"postal_code":"32575","place_name":"Parque Industrial Américas","place_type":"Zona industrial","county":"Juárez","state":"Chihuahua","city":"Juárez"},{"postal_code":"32575","place_name":"Misiones del Real","place_type":"Fraccionamiento","county":"Juárez","state":"Chihuahua","city":"Juárez"},{"postal_code":"32575","place_name":"Maquila Thomson","place_type":"Zona industrial","county":"Juárez","state":"Chihuahua","city":"Juárez"},{"postal_code":"32575","place_name":"Frida Kahlo","place_type":"Colonia","county":"Juárez","state":"Chihuahua","city":"Juárez"},{"postal_code":"32575","place_name":"Villas de Alcalá","place_type":"Fraccionamiento","county":"Juárez","state":"Chihuahua","city":"Juárez"},{"postal_code":"32575","place_name":"Parque Industrial PIMSA INTERMEX","place_type":"Zona industrial","county":"Juárez","state":"Chihuahua","city":"Juárez"},{"postal_code":"32575","place_name":"Urbivilla Bonita","place_type":"Fraccionamiento","county":"Juárez","state":"Chihuahua","city":"Juárez"},{"postal_code":"32575","place_name":"Lomas del Desierto II","place_type":"Fraccionamiento","county":"Juárez","state":"Chihuahua","city":"Juárez"},{"postal_code":"32575","place_name":"Cerradas del Sur","place_type":"Fraccionamiento","county":"Juárez","state":"Chihuahua","city":"Juárez"},{"postal_code":"32575","place_name":"Arecas","place_type":"Fraccionamiento","county":"Juárez","state":"Chihuahua","city":"Juárez"},{"postal_code":"32575","place_name":"Parque Industrial Salvarcar","place_type":"Zona industrial","county":"Juárez","state":"Chihuahua","city":"Juárez"},{"postal_code":"32575","place_name":"Torres del Sur","place_type":"Fraccionamiento","county":"Juárez","state":"Chihuahua","city":"Juárez"},{"postal_code":"32575","place_name":"Praderas de las Torres","place_type":"Fraccionamiento","county":"Juárez","state":"Chihuahua","city":"Juárez"},{"postal_code":"32575","place_name":"Profesora María Martínez","place_type":"Colonia","county":"Juárez","state":"Chihuahua","city":"Juárez"},{"postal_code":"32575","place_name":"Praderas del Sur","place_type":"Fraccionamiento","county":"Juárez","state":"Chihuahua","city":"Juárez"},{"postal_code":"32575","place_name":"Olivia Espinoza de Bermúdez","place_type":"Colonia","county":"Juárez","state":"Chihuahua","city":"Juárez"},{"postal_code":"32575","place_name":"Manuel Gómez Morín","place_type":"Fraccionamiento","county":"Juárez","state":"Chihuahua","city":"Juárez"},{"postal_code":"32575","place_name":"El Campanario 4 Siglos","place_type":"Fraccionamiento","county":"Juárez","state":"Chihuahua","city":"Juárez"},{"postal_code":"32575","place_name":"Parajes de San Isidro","place_type":"Fraccionamiento","county":"Juárez","state":"Chihuahua","city":"Juárez"},{"postal_code":"32575","place_name":"Senderos de San Isidro","place_type":"Fraccionamiento","county":"Juárez","state":"Chihuahua","city":"Juárez"},{"postal_code":"32575","place_name":"Parajes de San José","place_type":"Fraccionamiento","county":"Juárez","state":"Chihuahua","city":"Juárez"},{"postal_code":"32575","place_name":"Lomas del Desierto I","place_type":"Fraccionamiento","county":"Juárez","state":"Chihuahua","city":"Juárez"},{"postal_code":"32575","place_name":"Urbivilla del Campo","place_type":"Fraccionamiento","county":"Juárez","state":"Chihuahua","city":"Juárez"},{"postal_code":"32575","place_name":"Lomas del Desierto III","place_type":"Fraccionamiento","county":"Juárez","state":"Chihuahua","city":"Juárez"},{"postal_code":"32575","place_name":"Oporto","place_type":"Condominio","county":"Juárez","state":"Chihuahua","city":"Juárez"},{"postal_code":"32575","place_name":"Paseo del Castillo (Paseo de las Torres)","place_type":"Condominio","county":"Juárez","state":"Chihuahua","city":"Juárez"},{"postal_code":"32575","place_name":"Puerta Oriente","place_type":"Fraccionamiento","county":"Juárez","state":"Chihuahua","city":"Juárez"},{"postal_code":"32575","place_name":"Parque Industrial Intermex Sur","place_type":"Zona industrial","county":"Juárez","state":"Chihuahua","city":"Juárez"},{"postal_code":"32575","place_name":"Parque Industrial los Bravos","place_type":"Parque industrial","county":"Juárez","state":"Chihuahua","city":"Juárez"},{"postal_code":"32575","place_name":"Parajes del Sur","place_type":"Fraccionamiento","county":"Juárez","state":"Chihuahua","city":"Juárez"},{"postal_code":"32575","place_name":"Carlos Chavira Becerra","place_type":"Fraccionamiento","county":"Juárez","state":"Chihuahua","city":"Juárez"},{"postal_code":"32575","place_name":"Paraje de San Juan","place_type":"Fraccionamiento","county":"Juárez","state":"Chihuahua","city":"Juárez"},{"postal_code":"32575","place_name":"Las Haciendas Oriente","place_type":"Fraccionamiento","county":"Juárez","state":"Chihuahua","city":"Juárez"},{"postal_code":"32575","place_name":"Parajes de San Isidro II","place_type":"Fraccionamiento","county":"Juárez","state":"Chihuahua","city":"Juárez"},{"postal_code":"32575","place_name":"Portales de San Pedro","place_type":"Fraccionamiento","county":"Juárez","state":"Chihuahua","city":"Juárez"},{"postal_code":"32575","place_name":"Cerradas San Mateo","place_type":"Fraccionamiento","county":"Juárez","state":"Chihuahua","city":"Juárez"},{"postal_code":"32575","place_name":"Sierra Vista Sur","place_type":"Fraccionamiento","county":"Juárez","state":"Chihuahua","city":"Juárez"},{"postal_code":"32575","place_name":"Villas de Salvarcar","place_type":"Fraccionamiento","county":"Juárez","state":"Chihuahua","city":"Juárez"},{"postal_code":"32575","place_name":"Rinconada de las Torres","place_type":"Fraccionamiento","county":"Juárez","state":"Chihuahua","city":"Juárez"},{"postal_code":"32575","place_name":"Rincones de Salvarcar","place_type":"Fraccionamiento","county":"Juárez","state":"Chihuahua","city":"Juárez"},{"postal_code":"32575","place_name":"Valle Oriente","place_type":"Fraccionamiento","county":"Juárez","state":"Chihuahua","city":"Juárez"},{"postal_code":"32575","place_name":"Rincón de la Mesa","place_type":"Fraccionamiento","county":"Juárez","state":"Chihuahua","city":"Juárez"},{"postal_code":"32575","place_name":"Senderos del Sol","place_type":"Fraccionamiento","county":"Juárez","state":"Chihuahua","city":"Juárez"},{"postal_code":"32575","place_name":"Ixtapa (Paseo de las Torres)","place_type":"Condominio","county":"Juárez","state":"Chihuahua","city":"Juárez"},{"postal_code":"32575","place_name":"Profesora Simona Barba","place_type":"Fraccionamiento","county":"Juárez","state":"Chihuahua","city":"Juárez"},{"postal_code":"32575","place_name":"Municipio Libre","place_type":"Colonia","county":"Juárez","state":"Chihuahua","city":"Juárez"},{"postal_code":"32575","place_name":"Rincón del Sol","place_type":"Fraccionamiento","county":"Juárez","state":"Chihuahua","city":"Juárez"},{"postal_code":"32575","place_name":"Parque Industrial Independencia","place_type":"Parque industrial","county":"Juárez","state":"Chihuahua","city":"Juárez"},{"postal_code":"32575","place_name":"Real del Desierto","place_type":"Fraccionamiento","county":"Juárez","state":"Chihuahua","city":"Juárez"},{"postal_code":"32575","place_name":"Versalles Lyon","place_type":"Fraccionamiento","county":"Juárez","state":"Chihuahua","city":"Juárez"},{"postal_code":"32575","place_name":"Vallarta (Paseo de las Torres)","place_type":"Condominio","county":"Juárez","state":"Chihuahua","city":"Juárez"},{"postal_code":"32575","place_name":"Cerradas del Alamo","place_type":"Fraccionamiento","county":"Juárez","state":"Chihuahua","city":"Juárez"},{"postal_code":"32575","place_name":"Portal de Oriente","place_type":"Fraccionamiento","county":"Juárez","state":"Chihuahua","city":"Juárez"},{"postal_code":"32575","place_name":"Bosques de Salvarcar","place_type":"Fraccionamiento","county":"Juárez","state":"Chihuahua","city":"Juárez"},{"postal_code":"32575","place_name":"Sor Juana Inés de La Cruz","place_type":"Colonia","county":"Juárez","state":"Chihuahua","city":"Juárez"},{"postal_code":"32575","place_name":"Profesora Simona Barba","place_type":"Colonia","county":"Juárez","state":"Chihuahua","city":"Juárez"},{"postal_code":"32575","place_name":"Parajes de Oriente","place_type":"Fraccionamiento","county":"Juárez","state":"Chihuahua","city":"Juárez"},{"postal_code":"32575","place_name":"Jardines de Roma","place_type":"Fraccionamiento","county":"Juárez","state":"Chihuahua","city":"Juárez"},{"postal_code":"32575","place_name":"Hacienda Santa Fe","place_type":"Fraccionamiento","county":"Juárez","state":"Chihuahua","city":"Juárez"},{"postal_code":"32575","place_name":"Parque el Mirador","place_type":"Fraccionamiento","county":"Juárez","state":"Chihuahua","city":"Juárez"},{"postal_code":"32575","place_name":"Jardines de San Francisco","place_type":"Fraccionamiento","county":"Juárez","state":"Chihuahua","city":"Juárez"},{"postal_code":"32575","place_name":"Lisboa (Rinconada de las Torres)","place_type":"Condominio","county":"Juárez","state":"Chihuahua","city":"Juárez"},{"postal_code":"32575","place_name":"Pedregal de San Isidro","place_type":"Fraccionamiento","county":"Juárez","state":"Chihuahua","city":"Juárez"},{"postal_code":"32575","place_name":"Valle Fundadores","place_type":"Fraccionamiento","county":"Juárez","state":"Chihuahua","city":"Juárez"},{"postal_code":"32575","place_name":"Cerradas Santa Isabel","place_type":"Fraccionamiento","county":"Juárez","state":"Chihuahua","city":"Juárez"},{"postal_code":"32575","place_name":"Cerrada de San Pedro","place_type":"Fraccionamiento","county":"Juárez","state":"Chihuahua","city":"Juárez"},{"postal_code":"32575","place_name":"La Enramada","place_type":"Fraccionamiento","county":"Juárez","state":"Chihuahua","city":"Juárez"},{"postal_code":"32575","place_name":"Fray García de San Francisco","place_type":"Colonia","county":"Juárez","state":"Chihuahua","city":"Juárez"},{"postal_code":"32575","place_name":"Rinconada de las Torres IV","place_type":"Fraccionamiento","county":"Juárez","state":"Chihuahua","city":"Juárez"},{"postal_code":"32575","place_name":"Valle de Santiago","place_type":"Fraccionamiento","county":"Juárez","state":"Chihuahua","city":"Juárez"},{"postal_code":"32575","place_name":"Paseo de las Torres","place_type":"Fraccionamiento","county":"Juárez","state":"Chihuahua","city":"Juárez"},{"postal_code":"32575","place_name":"Valle de Allende","place_type":"Fraccionamiento","county":"Juárez","state":"Chihuahua","city":"Juárez"},{"postal_code":"32575","place_name":"Vistas de Zaragoza","place_type":"Fraccionamiento","county":"Juárez","state":"Chihuahua","city":"Juárez"},{"postal_code":"32575","place_name":"Oriente XXI Roma","place_type":"Fraccionamiento","county":"Juárez","state":"Chihuahua","city":"Juárez"},{"postal_code":"32575","place_name":"Urbivilla del Prado I","place_type":"Fraccionamiento","county":"Juárez","state":"Chihuahua","city":"Juárez"},{"postal_code":"32575","place_name":"Cerradas de Oriente I","place_type":"Fraccionamiento","county":"Juárez","state":"Chihuahua","city":"Juárez"},{"postal_code":"32575","place_name":"Cerradas de Oriente II","place_type":"Fraccionamiento","county":"Juárez","state":"Chihuahua","city":"Juárez"},{"postal_code":"32575","place_name":"Don Julio","place_type":"Fraccionamiento","county":"Juárez","state":"Chihuahua","city":"Juárez"},{"postal_code":"32575","place_name":"Misiones de Creel","place_type":"Fraccionamiento","county":"Juárez","state":"Chihuahua","city":"Juárez"},{"postal_code":"32575","place_name":"Parque Industrial Electrolux","place_type":"Zona industrial","county":"Juárez","state":"Chihuahua","city":"Juárez"},{"postal_code":"32575","place_name":"Perú (Rinconada de las Torres)","place_type":"Condominio","county":"Juárez","state":"Chihuahua","city":"Juárez"},{"postal_code":"32575","place_name":"Urbivilla del Prado","place_type":"Fraccionamiento","county":"Juárez","state":"Chihuahua","city":"Juárez"},{"postal_code":"32575","place_name":"Cerrada San Ángel","place_type":"Fraccionamiento","county":"Juárez","state":"Chihuahua","city":"Juárez"},{"postal_code":"32575","place_name":"Manuel J. Clouthier","place_type":"Colonia","county":"Juárez","state":"Chihuahua","city":"Juárez"},{"postal_code":"32575","place_name":"Carlos Castillo Peraza","place_type":"Colonia","county":"Juárez","state":"Chihuahua","city":"Juárez"},{"postal_code":"32575","place_name":"Urbivilla del Cedro","place_type":"Fraccionamiento","county":"Juárez","state":"Chihuahua","city":"Juárez"},{"postal_code":"32575","place_name":"Sierra Vista","place_type":"Fraccionamiento","county":"Juárez","state":"Chihuahua","city":"Juárez"}]