[{"postal_code":"34197","place_name":"Morelos Sur","place_type":"Colonia","county":"Durango","state":"Durango","city":"Victoria de Durango"},{"postal_code":"34197","place_name":"Praderas del Sur","place_type":"Colonia","county":"Durango","state":"Durango","city":"Victoria de Durango"},{"postal_code":"34197","place_name":"Loma Bonita","place_type":"Fraccionamiento","county":"Durango","state":"Durango","city":"Victoria de Durango"},{"postal_code":"34197","place_name":"Ampliación Morelos Sur","place_type":"Colonia","county":"Durango","state":"Durango","city":"Victoria de Durango"}]