[{"postal_code":"34955","place_name":"Los Pinos","place_type":"Colonia","county":"Pueblo Nuevo","state":"Durango","city":""},{"postal_code":"34955","place_name":"La Amistad","place_type":"Colonia","county":"Pueblo Nuevo","state":"Durango","city":""},{"postal_code":"34955","place_name":"Rinconcito","place_type":"Colonia","county":"Pueblo Nuevo","state":"Durango","city":""},{"postal_code":"34955","place_name":"Gabriel Amaya","place_type":"Ranchería","county":"Pueblo Nuevo","state":"Durango","city":""},{"postal_code":"34955","place_name":"Estadio","place_type":"Colonia","county":"Pueblo Nuevo","state":"Durango","city":""},{"postal_code":"34955","place_name":"Industrial","place_type":"Colonia","county":"Pueblo Nuevo","state":"Durango","city":""}]