[{"postal_code":"35050","place_name":"María Luisa Prado de Mayagoitia","place_type":"Colonia","county":"Gómez Palacio","state":"Durango","city":"Gómez Palacio"},{"postal_code":"35050","place_name":"Francisco Villa","place_type":"Colonia","county":"Gómez Palacio","state":"Durango","city":"Gómez Palacio"},{"postal_code":"35050","place_name":"Revolución","place_type":"Colonia","county":"Gómez Palacio","state":"Durango","city":"Gómez Palacio"},{"postal_code":"35050","place_name":"Bellavista","place_type":"Colonia","county":"Gómez Palacio","state":"Durango","city":"Gómez Palacio"},{"postal_code":"35050","place_name":"Francisco Zarco","place_type":"Colonia","county":"Gómez Palacio","state":"Durango","city":"Gómez Palacio"}]