[{"postal_code":"36560","place_name":"La Paz","place_type":"Fraccionamiento","county":"Irapuato","state":"Guanajuato","city":"Irapuato"},{"postal_code":"36560","place_name":"Los Arcos","place_type":"Colonia","county":"Irapuato","state":"Guanajuato","city":"Irapuato"},{"postal_code":"36560","place_name":"Distrito Federal","place_type":"Colonia","county":"Irapuato","state":"Guanajuato","city":"Irapuato"},{"postal_code":"36560","place_name":"Santa Anita","place_type":"Barrio","county":"Irapuato","state":"Guanajuato","city":"Irapuato"}]