[{"postal_code":"36976","place_name":"El Salitre","place_type":"Colonia","county":"Abasolo","state":"Guanajuato","city":"Abasolo"},{"postal_code":"36976","place_name":"Cruz Blanca","place_type":"Colonia","county":"Abasolo","state":"Guanajuato","city":"Abasolo"},{"postal_code":"36976","place_name":"Morelos","place_type":"Colonia","county":"Abasolo","state":"Guanajuato","city":"Abasolo"},{"postal_code":"36976","place_name":"San Juan II","place_type":"Colonia","county":"Abasolo","state":"Guanajuato","city":"Abasolo"},{"postal_code":"36976","place_name":"Tamazula","place_type":"Colonia","county":"Abasolo","state":"Guanajuato","city":"Abasolo"},{"postal_code":"36976","place_name":"Ampliación Miguel Hidalgo","place_type":"Colonia","county":"Abasolo","state":"Guanajuato","city":"Abasolo"},{"postal_code":"36976","place_name":"Vicente Guerrero","place_type":"Colonia","county":"Abasolo","state":"Guanajuato","city":"Abasolo"},{"postal_code":"36976","place_name":"Lourdes","place_type":"Colonia","county":"Abasolo","state":"Guanajuato","city":"Abasolo"},{"postal_code":"36976","place_name":"Loma Bonita","place_type":"Colonia","county":"Abasolo","state":"Guanajuato","city":"Abasolo"},{"postal_code":"36976","place_name":"Pirules","place_type":"Colonia","county":"Abasolo","state":"Guanajuato","city":"Abasolo"},{"postal_code":"36976","place_name":"Miguel Hidalgo","place_type":"Colonia","county":"Abasolo","state":"Guanajuato","city":"Abasolo"},{"postal_code":"36976","place_name":"La Cubana","place_type":"Colonia","county":"Abasolo","state":"Guanajuato","city":"Abasolo"},{"postal_code":"36976","place_name":"Cuitzeo de los Naranjos","place_type":"Fraccionamiento","county":"Abasolo","state":"Guanajuato","city":"Abasolo"}]