[{"postal_code":"37806","place_name":"El Jardín","place_type":"Fraccionamiento","county":"Dolores Hidalgo Cuna de la Independencia Nacional","state":"Guanajuato","city":"Dolores Hidalgo Cuna de la Independencia Nacional"},{"postal_code":"37806","place_name":"Fracción Ejido Dolores","place_type":"Colonia","county":"Dolores Hidalgo Cuna de la Independencia Nacional","state":"Guanajuato","city":"Dolores Hidalgo Cuna de la Independencia Nacional"},{"postal_code":"37806","place_name":"Loma Bonita","place_type":"Colonia","county":"Dolores Hidalgo Cuna de la Independencia Nacional","state":"Guanajuato","city":"Dolores Hidalgo Cuna de la Independencia Nacional"},{"postal_code":"37806","place_name":"Lomas del Sur","place_type":"Colonia","county":"Dolores Hidalgo Cuna de la Independencia Nacional","state":"Guanajuato","city":"Dolores Hidalgo Cuna de la Independencia Nacional"},{"postal_code":"37806","place_name":"Sagrado Corazón","place_type":"Colonia","county":"Dolores Hidalgo Cuna de la Independencia Nacional","state":"Guanajuato","city":"Dolores Hidalgo Cuna de la Independencia Nacional"},{"postal_code":"37806","place_name":"San Diego","place_type":"Colonia","county":"Dolores Hidalgo Cuna de la Independencia Nacional","state":"Guanajuato","city":"Dolores Hidalgo Cuna de la Independencia Nacional"},{"postal_code":"37806","place_name":"Independencia","place_type":"Fraccionamiento","county":"Dolores Hidalgo Cuna de la Independencia Nacional","state":"Guanajuato","city":"Dolores Hidalgo Cuna de la Independencia Nacional"},{"postal_code":"37806","place_name":"Niños Héroes","place_type":"Colonia","county":"Dolores Hidalgo Cuna de la Independencia Nacional","state":"Guanajuato","city":"Dolores Hidalgo Cuna de la Independencia Nacional"},{"postal_code":"37806","place_name":"Lindavista","place_type":"Colonia","county":"Dolores Hidalgo Cuna de la Independencia Nacional","state":"Guanajuato","city":"Dolores Hidalgo Cuna de la Independencia Nacional"},{"postal_code":"37806","place_name":"La Libertad","place_type":"Fraccionamiento","county":"Dolores Hidalgo Cuna de la Independencia Nacional","state":"Guanajuato","city":"Dolores Hidalgo Cuna de la Independencia Nacional"},{"postal_code":"37806","place_name":"San Antonio","place_type":"Colonia","county":"Dolores Hidalgo Cuna de la Independencia Nacional","state":"Guanajuato","city":"Dolores Hidalgo Cuna de la Independencia Nacional"},{"postal_code":"37806","place_name":"Dolores","place_type":"Ejido","county":"Dolores Hidalgo Cuna de la Independencia Nacional","state":"Guanajuato","city":"Dolores Hidalgo Cuna de la Independencia Nacional"},{"postal_code":"37806","place_name":"Valle del Sur","place_type":"Colonia","county":"Dolores Hidalgo Cuna de la Independencia Nacional","state":"Guanajuato","city":"Dolores Hidalgo Cuna de la Independencia Nacional"},{"postal_code":"37806","place_name":"Chapalita","place_type":"Colonia","county":"Dolores Hidalgo Cuna de la Independencia Nacional","state":"Guanajuato","city":"Dolores Hidalgo Cuna de la Independencia Nacional"},{"postal_code":"37806","place_name":"La Esperanza","place_type":"Fraccionamiento","county":"Dolores Hidalgo Cuna de la Independencia Nacional","state":"Guanajuato","city":"Dolores Hidalgo Cuna de la Independencia Nacional"},{"postal_code":"37806","place_name":"Ampliación Francisco I Madero","place_type":"Colonia","county":"Dolores Hidalgo Cuna de la Independencia Nacional","state":"Guanajuato","city":"Dolores Hidalgo Cuna de la Independencia Nacional"},{"postal_code":"37806","place_name":"Fortín de las Flores","place_type":"Colonia","county":"Dolores Hidalgo Cuna de la Independencia Nacional","state":"Guanajuato","city":"Dolores Hidalgo Cuna de la Independencia Nacional"},{"postal_code":"37806","place_name":"El Agave","place_type":"Fraccionamiento","county":"Dolores Hidalgo Cuna de la Independencia Nacional","state":"Guanajuato","city":"Dolores Hidalgo Cuna de la Independencia Nacional"},{"postal_code":"37806","place_name":"Jesús del Monte","place_type":"Colonia","county":"Dolores Hidalgo Cuna de la Independencia Nacional","state":"Guanajuato","city":"Dolores Hidalgo Cuna de la Independencia Nacional"},{"postal_code":"37806","place_name":"Montecarlo","place_type":"Fraccionamiento","county":"Dolores Hidalgo Cuna de la Independencia Nacional","state":"Guanajuato","city":"Dolores Hidalgo Cuna de la Independencia Nacional"},{"postal_code":"37806","place_name":"La Esperanza II","place_type":"Fraccionamiento","county":"Dolores Hidalgo Cuna de la Independencia Nacional","state":"Guanajuato","city":"Dolores Hidalgo Cuna de la Independencia Nacional"},{"postal_code":"37806","place_name":"Renacimiento","place_type":"Fraccionamiento","county":"Dolores Hidalgo Cuna de la Independencia Nacional","state":"Guanajuato","city":"Dolores Hidalgo Cuna de la Independencia Nacional"},{"postal_code":"37806","place_name":"15 de Septiembre","place_type":"Colonia","county":"Dolores Hidalgo Cuna de la Independencia Nacional","state":"Guanajuato","city":"Dolores Hidalgo Cuna de la Independencia Nacional"},{"postal_code":"37806","place_name":"Ampliación 15 de Septiembre","place_type":"Colonia","county":"Dolores Hidalgo Cuna de la Independencia Nacional","state":"Guanajuato","city":"Dolores Hidalgo Cuna de la Independencia Nacional"},{"postal_code":"37806","place_name":"Cocomacan","place_type":"Colonia","county":"Dolores Hidalgo Cuna de la Independencia Nacional","state":"Guanajuato","city":"Dolores Hidalgo Cuna de la Independencia Nacional"},{"postal_code":"37806","place_name":"El Jardín de la Loma","place_type":"Fraccionamiento","county":"Dolores Hidalgo Cuna de la Independencia Nacional","state":"Guanajuato","city":"Dolores Hidalgo Cuna de la Independencia Nacional"},{"postal_code":"37806","place_name":"Francisco I Madero","place_type":"Colonia","county":"Dolores Hidalgo Cuna de la Independencia Nacional","state":"Guanajuato","city":"Dolores Hidalgo Cuna de la Independencia Nacional"}]