[{"postal_code":"38405","place_name":"Ranchos Unidos","place_type":"Colonia","county":"Valle de Santiago","state":"Guanajuato","city":"Valle de Santiago"},{"postal_code":"38405","place_name":"Francisco Villa","place_type":"Colonia","county":"Valle de Santiago","state":"Guanajuato","city":"Valle de Santiago"},{"postal_code":"38405","place_name":"San Juanito","place_type":"Colonia","county":"Valle de Santiago","state":"Guanajuato","city":"Valle de Santiago"},{"postal_code":"38405","place_name":"La Loma","place_type":"Barrio","county":"Valle de Santiago","state":"Guanajuato","city":"Valle de Santiago"},{"postal_code":"38405","place_name":"Solidaridad","place_type":"Colonia","county":"Valle de Santiago","state":"Guanajuato","city":"Valle de Santiago"},{"postal_code":"38405","place_name":"El Chorrito","place_type":"Colonia","county":"Valle de Santiago","state":"Guanajuato","city":"Valle de Santiago"},{"postal_code":"38405","place_name":"Ignacio Ramírez","place_type":"Colonia","county":"Valle de Santiago","state":"Guanajuato","city":"Valle de Santiago"},{"postal_code":"38405","place_name":"Ampliación Francisco Villa","place_type":"Colonia","county":"Valle de Santiago","state":"Guanajuato","city":"Valle de Santiago"},{"postal_code":"38405","place_name":"Labradores","place_type":"Colonia","county":"Valle de Santiago","state":"Guanajuato","city":"Valle de Santiago"}]