[{"postal_code":"40893","place_name":"Miramar","place_type":"Colonia","county":"Zihuatanejo de Azueta","state":"Guerrero","city":"Zihuatanejo"},{"postal_code":"40893","place_name":"Agua de Correa","place_type":"Colonia","county":"Zihuatanejo de Azueta","state":"Guerrero","city":"Zihuatanejo"},{"postal_code":"40893","place_name":"CTM","place_type":"Colonia","county":"Zihuatanejo de Azueta","state":"Guerrero","city":"Zihuatanejo"},{"postal_code":"40893","place_name":"El Barril III","place_type":"Colonia","county":"Zihuatanejo de Azueta","state":"Guerrero","city":"Zihuatanejo"},{"postal_code":"40893","place_name":"El Barril","place_type":"Colonia","county":"Zihuatanejo de Azueta","state":"Guerrero","city":"Zihuatanejo"},{"postal_code":"40893","place_name":"16 de Mayo","place_type":"Colonia","county":"Zihuatanejo de Azueta","state":"Guerrero","city":"Zihuatanejo"},{"postal_code":"40893","place_name":"El Barril II","place_type":"Colonia","county":"Zihuatanejo de Azueta","state":"Guerrero","city":"Zihuatanejo"},{"postal_code":"40893","place_name":"La Presa","place_type":"Colonia","county":"Zihuatanejo de Azueta","state":"Guerrero","city":"Zihuatanejo"},{"postal_code":"40893","place_name":"20 de Noviembre","place_type":"Colonia","county":"Zihuatanejo de Azueta","state":"Guerrero","city":"Zihuatanejo"}]