[{"postal_code":"42156","place_name":"Palma 2da. Sección","place_type":"Colonia","county":"Ajacuba","state":"Hidalgo","city":""},{"postal_code":"42156","place_name":"Rincón Norte 1ra. Sección","place_type":"Colonia","county":"Ajacuba","state":"Hidalgo","city":""},{"postal_code":"42156","place_name":"Rincón Norte 2da. Sección","place_type":"Colonia","county":"Ajacuba","state":"Hidalgo","city":""},{"postal_code":"42156","place_name":"Santa Cruz Norte Centro","place_type":"Colonia","county":"Ajacuba","state":"Hidalgo","city":""},{"postal_code":"42156","place_name":"Santa Cruz Sur","place_type":"Colonia","county":"Ajacuba","state":"Hidalgo","city":""},{"postal_code":"42156","place_name":"Palma 1ra. Sección","place_type":"Colonia","county":"Ajacuba","state":"Hidalgo","city":""},{"postal_code":"42156","place_name":"Rincón Sur 2da. Sección","place_type":"Colonia","county":"Ajacuba","state":"Hidalgo","city":""},{"postal_code":"42156","place_name":"Rincón Sur 1ra. Sección","place_type":"Colonia","county":"Ajacuba","state":"Hidalgo","city":""}]