[{"postal_code":"42843","place_name":"La Loma","place_type":"Colonia","county":"Tula de Allende","state":"Hidalgo","city":"San Miguel Vindho"},{"postal_code":"42843","place_name":"La Loma","place_type":"Fraccionamiento","county":"Tula de Allende","state":"Hidalgo","city":"San Miguel Vindho"},{"postal_code":"42843","place_name":"Los Naranjos","place_type":"Colonia","county":"Tula de Allende","state":"Hidalgo","city":"San Miguel Vindho"},{"postal_code":"42843","place_name":"La Romera","place_type":"Colonia","county":"Tula de Allende","state":"Hidalgo","city":"San Miguel Vindho"}]