[{"postal_code":"45694","place_name":"Loma del Verde","place_type":"Fraccionamiento","county":"El Salto","state":"Jalisco","city":"San José el Verde (El Verde)"},{"postal_code":"45694","place_name":"La Guadalupana","place_type":"Colonia","county":"El Salto","state":"Jalisco","city":"San José el Verde (El Verde)"},{"postal_code":"45694","place_name":"Minerales","place_type":"Colonia","county":"El Salto","state":"Jalisco","city":"San José el Verde (El Verde)"},{"postal_code":"45694","place_name":"Buenos Aires","place_type":"Colonia","county":"El Salto","state":"Jalisco","city":"San José el Verde (El Verde)"},{"postal_code":"45694","place_name":"Loma de San Juan","place_type":"Colonia","county":"El Salto","state":"Jalisco","city":"San José el Verde (El Verde)"}]