[{"postal_code":"54474","place_name":"Vista Verde","place_type":"Fraccionamiento","county":"Nicolás Romero","state":"México","city":"Ciudad Nicolás Romero"},{"postal_code":"54474","place_name":"Granjas de Guadalupe 1a. Sección","place_type":"Colonia","county":"Nicolás Romero","state":"México","city":"Ciudad Nicolás Romero"},{"postal_code":"54474","place_name":"Clara Córdova Morán","place_type":"Colonia","county":"Nicolás Romero","state":"México","city":"Ciudad Nicolás Romero"},{"postal_code":"54474","place_name":"Ampliación Granjas de Guadalupe","place_type":"Colonia","county":"Nicolás Romero","state":"México","city":"Ciudad Nicolás Romero"}]