[{"postal_code":"55010","place_name":"Camino Nacional","place_type":"Fraccionamiento","county":"Ecatepec de Morelos","state":"México","city":"Ecatepec de Morelos"},{"postal_code":"55010","place_name":"Guadalupe Victoria","place_type":"Pueblo","county":"Ecatepec de Morelos","state":"México","city":"Ecatepec de Morelos"},{"postal_code":"55010","place_name":"El Obraje (Diamante)","place_type":"Colonia","county":"Ecatepec de Morelos","state":"México","city":"Ecatepec de Morelos"},{"postal_code":"55010","place_name":"Villa Esmeralda","place_type":"Conjunto habitacional","county":"Ecatepec de Morelos","state":"México","city":"Ecatepec de Morelos"},{"postal_code":"55010","place_name":"Rancho Victoria II","place_type":"Unidad habitacional","county":"Ecatepec de Morelos","state":"México","city":"Ecatepec de Morelos"},{"postal_code":"55010","place_name":"Rancho Victoria","place_type":"Conjunto habitacional","county":"Ecatepec de Morelos","state":"México","city":"Ecatepec de Morelos"},{"postal_code":"55010","place_name":"Mathzi I","place_type":"Colonia","county":"Ecatepec de Morelos","state":"México","city":"Ecatepec de Morelos"},{"postal_code":"55010","place_name":"El Diamante","place_type":"Colonia","county":"Ecatepec de Morelos","state":"México","city":"Ecatepec de Morelos"},{"postal_code":"55010","place_name":"Bonito Arboledas","place_type":"Fraccionamiento","county":"Ecatepec de Morelos","state":"México","city":"Ecatepec de Morelos"},{"postal_code":"55010","place_name":"Ampliación Guadalupe Victoria","place_type":"Colonia","county":"Ecatepec de Morelos","state":"México","city":"Ecatepec de Morelos"},{"postal_code":"55010","place_name":"El Progreso de Guadalupe Victoria","place_type":"Colonia","county":"Ecatepec de Morelos","state":"México","city":"Ecatepec de Morelos"},{"postal_code":"55010","place_name":"Barrio Nuevo Tultitlán","place_type":"Fraccionamiento","county":"Ecatepec de Morelos","state":"México","city":"Ecatepec de Morelos"},{"postal_code":"55010","place_name":"Los Lirios","place_type":"Fraccionamiento","county":"Ecatepec de Morelos","state":"México","city":"Ecatepec de Morelos"},{"postal_code":"55010","place_name":"Pozo de la Pila","place_type":"Unidad habitacional","county":"Ecatepec de Morelos","state":"México","city":"Ecatepec de Morelos"},{"postal_code":"55010","place_name":"Mathzi II","place_type":"Colonia","county":"Ecatepec de Morelos","state":"México","city":"Ecatepec de Morelos"},{"postal_code":"55010","place_name":"Mathzi III","place_type":"Colonia","county":"Ecatepec de Morelos","state":"México","city":"Ecatepec de Morelos"},{"postal_code":"55010","place_name":"Privada de Ecatepec","place_type":"Fraccionamiento","county":"Ecatepec de Morelos","state":"México","city":"Ecatepec de Morelos"},{"postal_code":"55010","place_name":"Las Piedras","place_type":"Colonia","county":"Ecatepec de Morelos","state":"México","city":"Ecatepec de Morelos"},{"postal_code":"55010","place_name":"El Manchon","place_type":"Colonia","county":"Ecatepec de Morelos","state":"México","city":"Ecatepec de Morelos"},{"postal_code":"55010","place_name":"Bonito las Flores","place_type":"Conjunto habitacional","county":"Ecatepec de Morelos","state":"México","city":"Ecatepec de Morelos"}]