[{"postal_code":"55400","place_name":"Aldeas I","place_type":"Unidad habitacional","county":"Ecatepec de Morelos","state":"México","city":"Ecatepec de Morelos"},{"postal_code":"55400","place_name":"ISSEMYM","place_type":"Unidad habitacional","county":"Ecatepec de Morelos","state":"México","city":"Ecatepec de Morelos"},{"postal_code":"55400","place_name":"Santa María Tulpetlac","place_type":"Pueblo","county":"Ecatepec de Morelos","state":"México","city":"Ecatepec de Morelos"},{"postal_code":"55400","place_name":"Nieves","place_type":"Unidad habitacional","county":"Ecatepec de Morelos","state":"México","city":"Ecatepec de Morelos"},{"postal_code":"55400","place_name":"Aldeas II","place_type":"Unidad habitacional","county":"Ecatepec de Morelos","state":"México","city":"Ecatepec de Morelos"}]