[{"postal_code":"55716","place_name":"Jardines de San José 1a Secc","place_type":"Fraccionamiento","county":"Coacalco de Berriozábal","state":"México","city":"Coacalco de Berriozabal"},{"postal_code":"55716","place_name":"Sección las Villas (Unidad Coacalco)","place_type":"Fraccionamiento","county":"Coacalco de Berriozábal","state":"México","city":"Coacalco de Berriozabal"},{"postal_code":"55716","place_name":"Jardines de San José 2a Secc","place_type":"Fraccionamiento","county":"Coacalco de Berriozábal","state":"México","city":"Coacalco de Berriozabal"}]