[{"postal_code":"58095","place_name":"Rector Díaz Rubio","place_type":"Colonia","county":"Morelia","state":"Michoacán de Ocampo","city":"Morelia"},{"postal_code":"58095","place_name":"Torrecillas del Sur","place_type":"Colonia","county":"Morelia","state":"Michoacán de Ocampo","city":"Morelia"},{"postal_code":"58095","place_name":"Loma Larga","place_type":"Colonia","county":"Morelia","state":"Michoacán de Ocampo","city":"Morelia"},{"postal_code":"58095","place_name":"Lomas del Sur III","place_type":"Fraccionamiento","county":"Morelia","state":"Michoacán de Ocampo","city":"Morelia"},{"postal_code":"58095","place_name":"Valle Dorado del Sur","place_type":"Fraccionamiento","county":"Morelia","state":"Michoacán de Ocampo","city":"Morelia"},{"postal_code":"58095","place_name":"Lomas de la Joya","place_type":"Conjunto habitacional","county":"Morelia","state":"Michoacán de Ocampo","city":"Morelia"},{"postal_code":"58095","place_name":"Buenos Aires","place_type":"Colonia","county":"Morelia","state":"Michoacán de Ocampo","city":"Morelia"},{"postal_code":"58095","place_name":"Loma Larga Oriente","place_type":"Colonia","county":"Morelia","state":"Michoacán de Ocampo","city":"Morelia"},{"postal_code":"58095","place_name":"Villas del Sur III","place_type":"Unidad habitacional","county":"Morelia","state":"Michoacán de Ocampo","city":"Morelia"},{"postal_code":"58095","place_name":"Loma Dorada del Sur","place_type":"Colonia","county":"Morelia","state":"Michoacán de Ocampo","city":"Morelia"},{"postal_code":"58095","place_name":"Cerro Verde","place_type":"Fraccionamiento","county":"Morelia","state":"Michoacán de Ocampo","city":"Morelia"},{"postal_code":"58095","place_name":"Valle El Rosario","place_type":"Colonia","county":"Morelia","state":"Michoacán de Ocampo","city":"Morelia"},{"postal_code":"58095","place_name":"Loma de Chapultepec","place_type":"Fraccionamiento","county":"Morelia","state":"Michoacán de Ocampo","city":"Morelia"},{"postal_code":"58095","place_name":"Torres Altavista","place_type":"Colonia","county":"Morelia","state":"Michoacán de Ocampo","city":"Morelia"},{"postal_code":"58095","place_name":"Villas del Sur II","place_type":"Conjunto habitacional","county":"Morelia","state":"Michoacán de Ocampo","city":"Morelia"},{"postal_code":"58095","place_name":"Praderas del Sur II","place_type":"Colonia","county":"Morelia","state":"Michoacán de Ocampo","city":"Morelia"},{"postal_code":"58095","place_name":"La Ciudadela","place_type":"Fraccionamiento","county":"Morelia","state":"Michoacán de Ocampo","city":"Morelia"},{"postal_code":"58095","place_name":"Rincón San Diego","place_type":"Unidad habitacional","county":"Morelia","state":"Michoacán de Ocampo","city":"Morelia"},{"postal_code":"58095","place_name":"Lomas","place_type":"Fraccionamiento","county":"Morelia","state":"Michoacán de Ocampo","city":"Morelia"},{"postal_code":"58095","place_name":"Jardines del Sur","place_type":"Colonia","county":"Morelia","state":"Michoacán de Ocampo","city":"Morelia"},{"postal_code":"58095","place_name":"Misión de San Diego","place_type":"Conjunto habitacional","county":"Morelia","state":"Michoacán de Ocampo","city":"Morelia"},{"postal_code":"58095","place_name":"Campo Real","place_type":"Colonia","county":"Morelia","state":"Michoacán de Ocampo","city":"Morelia"},{"postal_code":"58095","place_name":"Felipe Sandoval","place_type":"Colonia","county":"Morelia","state":"Michoacán de Ocampo","city":"Morelia"},{"postal_code":"58095","place_name":"Loma Bonita del Sur","place_type":"Colonia","county":"Morelia","state":"Michoacán de Ocampo","city":"Morelia"},{"postal_code":"58095","place_name":"Praderas Paraíso","place_type":"Fraccionamiento","county":"Morelia","state":"Michoacán de Ocampo","city":"Morelia"},{"postal_code":"58095","place_name":"Villas del Sur","place_type":"Fraccionamiento","county":"Morelia","state":"Michoacán de Ocampo","city":"Morelia"},{"postal_code":"58095","place_name":"Los Tucanes","place_type":"Colonia","county":"Morelia","state":"Michoacán de Ocampo","city":"Morelia"},{"postal_code":"58095","place_name":"Puerto Banus","place_type":"Colonia","county":"Morelia","state":"Michoacán de Ocampo","city":"Morelia"},{"postal_code":"58095","place_name":"La Morita (Colonia la Morita)","place_type":"Colonia","county":"Morelia","state":"Michoacán de Ocampo","city":"Morelia"},{"postal_code":"58095","place_name":"Mirador del Valle","place_type":"Colonia","county":"Morelia","state":"Michoacán de Ocampo","city":"Morelia"},{"postal_code":"58095","place_name":"Colinas del Sur","place_type":"Fraccionamiento","county":"Morelia","state":"Michoacán de Ocampo","city":"Morelia"},{"postal_code":"58095","place_name":"Pradera del Sur","place_type":"Colonia","county":"Morelia","state":"Michoacán de Ocampo","city":"Morelia"},{"postal_code":"58095","place_name":"Progreso del Sur","place_type":"Colonia","county":"Morelia","state":"Michoacán de Ocampo","city":"Morelia"},{"postal_code":"58095","place_name":"Valle de los Arcos","place_type":"Colonia","county":"Morelia","state":"Michoacán de Ocampo","city":"Morelia"},{"postal_code":"58095","place_name":"Peña Blanca","place_type":"Colonia","county":"Morelia","state":"Michoacán de Ocampo","city":"Morelia"},{"postal_code":"58095","place_name":"Puerta Blanca","place_type":"Colonia","county":"Morelia","state":"Michoacán de Ocampo","city":"Morelia"},{"postal_code":"58095","place_name":"Lomas del Sur II","place_type":"Fraccionamiento","county":"Morelia","state":"Michoacán de Ocampo","city":"Morelia"},{"postal_code":"58095","place_name":"Rafael Dávalos","place_type":"Fraccionamiento","county":"Morelia","state":"Michoacán de Ocampo","city":"Morelia"},{"postal_code":"58095","place_name":"Praderas de la Loma","place_type":"Fraccionamiento","county":"Morelia","state":"Michoacán de Ocampo","city":"Morelia"},{"postal_code":"58095","place_name":"Loma Blanca","place_type":"Fraccionamiento","county":"Morelia","state":"Michoacán de Ocampo","city":"Morelia"},{"postal_code":"58095","place_name":"Lomas del Sur","place_type":"Fraccionamiento","county":"Morelia","state":"Michoacán de Ocampo","city":"Morelia"},{"postal_code":"58095","place_name":"Montevista","place_type":"Fraccionamiento","county":"Morelia","state":"Michoacán de Ocampo","city":"Morelia"},{"postal_code":"58095","place_name":"Los Mirasoles","place_type":"Fraccionamiento","county":"Morelia","state":"Michoacán de Ocampo","city":"Morelia"}]