[{"postal_code":"58190","place_name":"Rector Hidalgo","place_type":"Colonia","county":"Morelia","state":"Michoacán de Ocampo","city":"Morelia"},{"postal_code":"58190","place_name":"Santa Catalina","place_type":"Unidad habitacional","county":"Morelia","state":"Michoacán de Ocampo","city":"Morelia"},{"postal_code":"58190","place_name":"Agustín Arriaga Rivera","place_type":"Colonia","county":"Morelia","state":"Michoacán de Ocampo","city":"Morelia"},{"postal_code":"58190","place_name":"Valladolid","place_type":"Fraccionamiento","county":"Morelia","state":"Michoacán de Ocampo","city":"Morelia"},{"postal_code":"58190","place_name":"INDECO Expropiación Petrolera","place_type":"Unidad habitacional","county":"Morelia","state":"Michoacán de Ocampo","city":"Morelia"},{"postal_code":"58190","place_name":"Alcaide Ignacio Pérez","place_type":"Colonia","county":"Morelia","state":"Michoacán de Ocampo","city":"Morelia"},{"postal_code":"58190","place_name":"Nueva Valladolid","place_type":"Colonia","county":"Morelia","state":"Michoacán de Ocampo","city":"Morelia"},{"postal_code":"58190","place_name":"Real Valladolid","place_type":"Conjunto habitacional","county":"Morelia","state":"Michoacán de Ocampo","city":"Morelia"}]