[{"postal_code":"63311","place_name":"Magisterial","place_type":"Colonia","county":"Santiago Ixcuintla","state":"Nayarit","city":"Santiago Ixcuintla"},{"postal_code":"63311","place_name":"El Mirador","place_type":"Colonia","county":"Santiago Ixcuintla","state":"Nayarit","city":"Santiago Ixcuintla"},{"postal_code":"63311","place_name":"Ramón López Velarde","place_type":"Colonia","county":"Santiago Ixcuintla","state":"Nayarit","city":"Santiago Ixcuintla"},{"postal_code":"63311","place_name":"Universidad","place_type":"Fraccionamiento","county":"Santiago Ixcuintla","state":"Nayarit","city":"Santiago Ixcuintla"}]