[{"postal_code":"68016","place_name":"Solidaridad","place_type":"Colonia","county":"Oaxaca de Juárez","state":"Oaxaca","city":"Oaxaca de Juárez"},{"postal_code":"68016","place_name":"Hoteleros","place_type":"Colonia","county":"Oaxaca de Juárez","state":"Oaxaca","city":"Oaxaca de Juárez"},{"postal_code":"68016","place_name":"La Soledad","place_type":"Colonia","county":"Oaxaca de Juárez","state":"Oaxaca","city":"Oaxaca de Juárez"},{"postal_code":"68016","place_name":"Loma Bonita","place_type":"Colonia","county":"Oaxaca de Juárez","state":"Oaxaca","city":"Oaxaca de Juárez"},{"postal_code":"68016","place_name":"El Paraíso","place_type":"Colonia","county":"Oaxaca de Juárez","state":"Oaxaca","city":"Oaxaca de Juárez"},{"postal_code":"68016","place_name":"Buena Vista","place_type":"Colonia","county":"Oaxaca de Juárez","state":"Oaxaca","city":"Oaxaca de Juárez"},{"postal_code":"68016","place_name":"Lomas Panoramicas","place_type":"Colonia","county":"Oaxaca de Juárez","state":"Oaxaca","city":"Oaxaca de Juárez"},{"postal_code":"68016","place_name":"10 de Abril","place_type":"Colonia","county":"Oaxaca de Juárez","state":"Oaxaca","city":"Oaxaca de Juárez"},{"postal_code":"68016","place_name":"Del Maestro","place_type":"Colonia","county":"Oaxaca de Juárez","state":"Oaxaca","city":"Oaxaca de Juárez"},{"postal_code":"68016","place_name":"Vista Hermosa","place_type":"Colonia","county":"Oaxaca de Juárez","state":"Oaxaca","city":"Oaxaca de Juárez"}]