[{"postal_code":"70023","place_name":"Lorenza Santiago Esteva","place_type":"Colonia","county":"Heroica Ciudad de Juchitán de Zaragoza","state":"Oaxaca","city":"Juchitán (Juchitán de Zaragoza)"},{"postal_code":"70023","place_name":"16 de Septiembre","place_type":"Colonia","county":"Heroica Ciudad de Juchitán de Zaragoza","state":"Oaxaca","city":"Juchitán (Juchitán de Zaragoza)"},{"postal_code":"70023","place_name":"15 de Agosto","place_type":"Colonia","county":"Heroica Ciudad de Juchitán de Zaragoza","state":"Oaxaca","city":"Juchitán (Juchitán de Zaragoza)"},{"postal_code":"70023","place_name":"Santa Cruz de los Pescadores","place_type":"Colonia","county":"Heroica Ciudad de Juchitán de Zaragoza","state":"Oaxaca","city":"Juchitán (Juchitán de Zaragoza)"},{"postal_code":"70023","place_name":"103","place_type":"Colonia","county":"Heroica Ciudad de Juchitán de Zaragoza","state":"Oaxaca","city":"Juchitán (Juchitán de Zaragoza)"}]