[{"postal_code":"70045","place_name":"Victor Yodo","place_type":"Colonia","county":"Heroica Ciudad de Juchitán de Zaragoza","state":"Oaxaca","city":"Juchitán (Juchitán de Zaragoza)"},{"postal_code":"70045","place_name":"Héroes de Chapultepec","place_type":"Colonia","county":"Heroica Ciudad de Juchitán de Zaragoza","state":"Oaxaca","city":"Juchitán (Juchitán de Zaragoza)"},{"postal_code":"70045","place_name":"15 de Septiembre","place_type":"Colonia","county":"Heroica Ciudad de Juchitán de Zaragoza","state":"Oaxaca","city":"Juchitán (Juchitán de Zaragoza)"}]