[{"postal_code":"73178","place_name":"Zacamila","place_type":"Colonia","county":"Huauchinango","state":"Puebla","city":"Huauchinango"},{"postal_code":"73178","place_name":"Quetzalcoatl","place_type":"Fraccionamiento","county":"Huauchinango","state":"Puebla","city":"Huauchinango"},{"postal_code":"73178","place_name":"Vima","place_type":"Colonia","county":"Huauchinango","state":"Puebla","city":"Huauchinango"},{"postal_code":"73178","place_name":"Benito Juárez","place_type":"Colonia","county":"Huauchinango","state":"Puebla","city":"Huauchinango"},{"postal_code":"73178","place_name":"La Palpa","place_type":"Colonia","county":"Huauchinango","state":"Puebla","city":"Huauchinango"},{"postal_code":"73178","place_name":"Lomas del Bosque","place_type":"Fraccionamiento","county":"Huauchinango","state":"Puebla","city":"Huauchinango"},{"postal_code":"73178","place_name":"Los Ángeles","place_type":"Colonia","county":"Huauchinango","state":"Puebla","city":"Huauchinango"}]