[{"postal_code":"76643","place_name":"San Pablo (San Pablo Tolimán)","place_type":"Colonia","county":"Tolimán","state":"Querétaro","city":""},{"postal_code":"76643","place_name":"Lomas Bonitas","place_type":"Colonia","county":"Tolimán","state":"Querétaro","city":""},{"postal_code":"76643","place_name":"Campesina","place_type":"Colonia","county":"Tolimán","state":"Querétaro","city":""},{"postal_code":"76643","place_name":"La Villita","place_type":"Colonia","county":"Tolimán","state":"Querétaro","city":""}]