[{"postal_code":"78173","place_name":"Industrial Aviación 2a Sección","place_type":"Colonia","county":"San Luis Potosí","state":"San Luis Potosí","city":"San Luis Potosí"},{"postal_code":"78173","place_name":"San Guillermo","place_type":"Fraccionamiento","county":"San Luis Potosí","state":"San Luis Potosí","city":"San Luis Potosí"},{"postal_code":"78173","place_name":"Tláloc","place_type":"Colonia","county":"San Luis Potosí","state":"San Luis Potosí","city":"San Luis Potosí"},{"postal_code":"78173","place_name":"Del Bosque","place_type":"Colonia","county":"San Luis Potosí","state":"San Luis Potosí","city":"San Luis Potosí"},{"postal_code":"78173","place_name":"Privada Felipe Ángeles","place_type":"Fraccionamiento","county":"San Luis Potosí","state":"San Luis Potosí","city":"San Luis Potosí"}]