[{"postal_code":"80290","place_name":"Lázaro Cárdenas","place_type":"Colonia","county":"Culiacán","state":"Sinaloa","city":"Culiacán Rosales"},{"postal_code":"80290","place_name":"Lázaro Cárdenas","place_type":"Ampliación","county":"Culiacán","state":"Sinaloa","city":"Culiacán Rosales"},{"postal_code":"80290","place_name":"Simon Bolívar","place_type":"Colonia","county":"Culiacán","state":"Sinaloa","city":"Culiacán Rosales"},{"postal_code":"80290","place_name":"Providencia","place_type":"Fraccionamiento","county":"Culiacán","state":"Sinaloa","city":"Culiacán Rosales"},{"postal_code":"80290","place_name":"Las Huertas","place_type":"Colonia","county":"Culiacán","state":"Sinaloa","city":"Culiacán Rosales"}]