[{"postal_code":"82128","place_name":"Privanza","place_type":"Fraccionamiento","county":"Mazatlán","state":"Sinaloa","city":"Mazatlán"},{"postal_code":"82128","place_name":"Los Mangos II","place_type":"Fraccionamiento","county":"Mazatlán","state":"Sinaloa","city":"Mazatlán"},{"postal_code":"82128","place_name":"INFONAVIT Playas","place_type":"Unidad habitacional","county":"Mazatlán","state":"Sinaloa","city":"Mazatlán"},{"postal_code":"82128","place_name":"Los Mangos I","place_type":"Fraccionamiento","county":"Mazatlán","state":"Sinaloa","city":"Mazatlán"},{"postal_code":"82128","place_name":"Hacienda Los Mangos","place_type":"Fraccionamiento","county":"Mazatlán","state":"Sinaloa","city":"Mazatlán"}]