[{"postal_code":"83100","place_name":"Ley 57","place_type":"Colonia","county":"Hermosillo","state":"Sonora","city":"Hermosillo"},{"postal_code":"83100","place_name":"San Diego","place_type":"Fraccionamiento","county":"Hermosillo","state":"Sonora","city":"Hermosillo"},{"postal_code":"83100","place_name":"Prados de Bugambilias II","place_type":"Colonia","county":"Hermosillo","state":"Sonora","city":"Hermosillo"},{"postal_code":"83100","place_name":"Residencial Kino","place_type":"Colonia","county":"Hermosillo","state":"Sonora","city":"Hermosillo"},{"postal_code":"83100","place_name":"Cerrada del Carmen","place_type":"Colonia","county":"Hermosillo","state":"Sonora","city":"Hermosillo"},{"postal_code":"83100","place_name":"Privada C贸rdoba","place_type":"Colonia","county":"Hermosillo","state":"Sonora","city":"Hermosillo"},{"postal_code":"83100","place_name":"Popular","place_type":"Colonia","county":"Hermosillo","state":"Sonora","city":"Hermosillo"},{"postal_code":"83100","place_name":"Prados de Bugambilias","place_type":"Colonia","county":"Hermosillo","state":"Sonora","city":"Hermosillo"},{"postal_code":"83100","place_name":"Privada Robles","place_type":"Colonia","county":"Hermosillo","state":"Sonora","city":"Hermosillo"},{"postal_code":"83100","place_name":"Apolo","place_type":"Colonia","county":"Hermosillo","state":"Sonora","city":"Hermosillo"},{"postal_code":"83100","place_name":"Prados del Sol","place_type":"Colonia","county":"Hermosillo","state":"Sonora","city":"Hermosillo"},{"postal_code":"83100","place_name":"Atardeceres","place_type":"Colonia","county":"Hermosillo","state":"Sonora","city":"Hermosillo"},{"postal_code":"83100","place_name":"Misi贸n Del Sol","place_type":"Fraccionamiento","county":"Hermosillo","state":"Sonora","city":"Hermosillo"},{"postal_code":"83100","place_name":"Misi贸n San Ignacio","place_type":"Fraccionamiento","county":"Hermosillo","state":"Sonora","city":"Hermosillo"},{"postal_code":"83100","place_name":"15 "A"","place_type":"Colonia","county":"Hermosillo","state":"Sonora","city":"Hermosillo"},{"postal_code":"83100","place_name":"Misi贸n Del Real","place_type":"Fraccionamiento","county":"Hermosillo","state":"Sonora","city":"Hermosillo"}]