[{"postal_code":"83294","place_name":"Valle del Marquez","place_type":"Fraccionamiento","county":"Hermosillo","state":"Sonora","city":"Hermosillo"},{"postal_code":"83294","place_name":"Cuauhtémoc","place_type":"Colonia","county":"Hermosillo","state":"Sonora","city":"Hermosillo"},{"postal_code":"83294","place_name":"Los Álamos","place_type":"Colonia","county":"Hermosillo","state":"Sonora","city":"Hermosillo"},{"postal_code":"83294","place_name":"Perisur","place_type":"Fraccionamiento","county":"Hermosillo","state":"Sonora","city":"Hermosillo"},{"postal_code":"83294","place_name":"Rincón Del Marquez","place_type":"Colonia","county":"Hermosillo","state":"Sonora","city":"Hermosillo"}]