[{"postal_code":"85199","place_name":"Robles Del Castillo","place_type":"Colonia","county":"Cajeme","state":"Sonora","city":"Ciudad Obregón"},{"postal_code":"85199","place_name":"Misión San Gabriel","place_type":"Fraccionamiento","county":"Cajeme","state":"Sonora","city":"Ciudad Obregón"},{"postal_code":"85199","place_name":"Pradera Bonita","place_type":"Fraccionamiento","county":"Cajeme","state":"Sonora","city":"Ciudad Obregón"},{"postal_code":"85199","place_name":"Luis Echeverría Álvarez (Álvaro Obregón)","place_type":"Colonia","county":"Cajeme","state":"Sonora","city":"Ciudad Obregón"}]