[{"postal_code":"85425","place_name":"Ocotillo II","place_type":"Unidad habitacional","county":"Guaymas","state":"Sonora","city":"Heroica Guaymas"},{"postal_code":"85425","place_name":"Guaymas Norte","place_type":"Unidad habitacional","county":"Guaymas","state":"Sonora","city":"Heroica Guaymas"},{"postal_code":"85425","place_name":"Los Lagos","place_type":"Fraccionamiento","county":"Guaymas","state":"Sonora","city":"Heroica Guaymas"},{"postal_code":"85425","place_name":"Ocotillo","place_type":"Fraccionamiento","county":"Guaymas","state":"Sonora","city":"Heroica Guaymas"},{"postal_code":"85425","place_name":"San Geronimo","place_type":"Fraccionamiento","county":"Guaymas","state":"Sonora","city":"Heroica Guaymas"},{"postal_code":"85425","place_name":"Villas del Puerto","place_type":"Fraccionamiento","county":"Guaymas","state":"Sonora","city":"Heroica Guaymas"}]