[{"postal_code":"85874","place_name":"Villa Dorada","place_type":"Colonia","county":"Navojoa","state":"Sonora","city":"Navojoa"},{"postal_code":"85874","place_name":"Los Laureles","place_type":"Fraccionamiento","county":"Navojoa","state":"Sonora","city":"Navojoa"},{"postal_code":"85874","place_name":"La Joya","place_type":"Fraccionamiento","county":"Navojoa","state":"Sonora","city":"Navojoa"},{"postal_code":"85874","place_name":"Bugambilias","place_type":"Fraccionamiento","county":"Navojoa","state":"Sonora","city":"Navojoa"},{"postal_code":"85874","place_name":"Los Girasoles","place_type":"Fraccionamiento","county":"Navojoa","state":"Sonora","city":"Navojoa"}]