[{"postal_code":"89607","place_name":"Jardines de Altamira","place_type":"Fraccionamiento","county":"Altamira","state":"Tamaulipas","city":"Altamira"},{"postal_code":"89607","place_name":"Los Naranjos","place_type":"Fraccionamiento","county":"Altamira","state":"Tamaulipas","city":"Altamira"},{"postal_code":"89607","place_name":"Los Sábalos","place_type":"Colonia","county":"Altamira","state":"Tamaulipas","city":"Altamira"},{"postal_code":"89607","place_name":"El Campanario","place_type":"Fraccionamiento","county":"Altamira","state":"Tamaulipas","city":"Altamira"},{"postal_code":"89607","place_name":"Santa Anita","place_type":"Fraccionamiento","county":"Altamira","state":"Tamaulipas","city":"Altamira"},{"postal_code":"89607","place_name":"Villas de Champayán","place_type":"Fraccionamiento","county":"Altamira","state":"Tamaulipas","city":"Altamira"},{"postal_code":"89607","place_name":"FOVISSSTE","place_type":"Unidad habitacional","county":"Altamira","state":"Tamaulipas","city":"Altamira"},{"postal_code":"89607","place_name":"Privada Santiago","place_type":"Unidad habitacional","county":"Altamira","state":"Tamaulipas","city":"Altamira"},{"postal_code":"89607","place_name":"Altamira","place_type":"Fraccionamiento","county":"Altamira","state":"Tamaulipas","city":"Altamira"},{"postal_code":"89607","place_name":"Santa Ana","place_type":"Colonia","county":"Altamira","state":"Tamaulipas","city":"Altamira"},{"postal_code":"89607","place_name":"Laguna Florida","place_type":"Fraccionamiento","county":"Altamira","state":"Tamaulipas","city":"Altamira"},{"postal_code":"89607","place_name":"Jardines de Champayán","place_type":"Colonia","county":"Altamira","state":"Tamaulipas","city":"Altamira"},{"postal_code":"89607","place_name":"Pescadores 2","place_type":"Colonia","county":"Altamira","state":"Tamaulipas","city":"Altamira"},{"postal_code":"89607","place_name":"Puerto Escondido","place_type":"Colonia","county":"Altamira","state":"Tamaulipas","city":"Altamira"},{"postal_code":"89607","place_name":"Enrique Cárdenas Centro","place_type":"Colonia","county":"Altamira","state":"Tamaulipas","city":"Altamira"},{"postal_code":"89607","place_name":"Las Grullas","place_type":"Unidad habitacional","county":"Altamira","state":"Tamaulipas","city":"Altamira"},{"postal_code":"89607","place_name":"Pescadores","place_type":"Colonia","county":"Altamira","state":"Tamaulipas","city":"Altamira"},{"postal_code":"89607","place_name":"Villas de Champayán 2","place_type":"Fraccionamiento","county":"Altamira","state":"Tamaulipas","city":"Altamira"},{"postal_code":"89607","place_name":"Alameda","place_type":"Unidad habitacional","county":"Altamira","state":"Tamaulipas","city":"Altamira"},{"postal_code":"89607","place_name":"INFONAVIT Fidel Velázquez","place_type":"Colonia","county":"Altamira","state":"Tamaulipas","city":"Altamira"},{"postal_code":"89607","place_name":"Los Almendros","place_type":"Colonia","county":"Altamira","state":"Tamaulipas","city":"Altamira"},{"postal_code":"89607","place_name":"Ixtapa","place_type":"Colonia","county":"Altamira","state":"Tamaulipas","city":"Altamira"},{"postal_code":"89607","place_name":"La Florida","place_type":"Colonia","county":"Altamira","state":"Tamaulipas","city":"Altamira"},{"postal_code":"89607","place_name":"Altamira II","place_type":"Unidad habitacional","county":"Altamira","state":"Tamaulipas","city":"Altamira"},{"postal_code":"89607","place_name":"Las Marismas","place_type":"Fraccionamiento","county":"Altamira","state":"Tamaulipas","city":"Altamira"},{"postal_code":"89607","place_name":"Revolución Verde","place_type":"Colonia","county":"Altamira","state":"Tamaulipas","city":"Altamira"},{"postal_code":"89607","place_name":"Tercer Milenium","place_type":"Fraccionamiento","county":"Altamira","state":"Tamaulipas","city":"Altamira"}]