[{"postal_code":"93393","place_name":"Los Pinos","place_type":"Colonia","county":"Poza Rica de Hidalgo","state":"Veracruz de Ignacio de la Llave","city":"Poza Rica de Hidalgo"},{"postal_code":"93393","place_name":"Del Policia","place_type":"Colonia","county":"Poza Rica de Hidalgo","state":"Veracruz de Ignacio de la Llave","city":"Poza Rica de Hidalgo"},{"postal_code":"93393","place_name":"10 de Abril","place_type":"Colonia","county":"Poza Rica de Hidalgo","state":"Veracruz de Ignacio de la Llave","city":"Poza Rica de Hidalgo"},{"postal_code":"93393","place_name":"Vicente Herrera","place_type":"Colonia","county":"Poza Rica de Hidalgo","state":"Veracruz de Ignacio de la Llave","city":"Poza Rica de Hidalgo"},{"postal_code":"93393","place_name":"Oscar Torres Pancardo","place_type":"Colonia","county":"Poza Rica de Hidalgo","state":"Veracruz de Ignacio de la Llave","city":"Poza Rica de Hidalgo"},{"postal_code":"93393","place_name":"Fernando Gutiérrez Barrios","place_type":"Colonia","county":"Poza Rica de Hidalgo","state":"Veracruz de Ignacio de la Llave","city":"Poza Rica de Hidalgo"},{"postal_code":"93393","place_name":"Niños Héroes","place_type":"Colonia","county":"Poza Rica de Hidalgo","state":"Veracruz de Ignacio de la Llave","city":"Poza Rica de Hidalgo"}]